alibabacloud_waf_openapi20190910/__init__.py
alibabacloud_waf_openapi20190910/client.py
alibabacloud_waf_openapi20190910/models.py
alibabacloud_waf_openapi20190910_py2-1.1.4.dist-info/LICENSE
alibabacloud_waf_openapi20190910_py2-1.1.4.dist-info/METADATA
alibabacloud_waf_openapi20190910_py2-1.1.4.dist-info/WHEEL
alibabacloud_waf_openapi20190910_py2-1.1.4.dist-info/top_level.txt
alibabacloud_waf_openapi20190910_py2-1.1.4.dist-info/RECORD
